{
  "meta": {
    "game_name": "cladder",
    "experiment_name": "full_v1.5_default",
    "game_id": 6020,
    "results_folder": "llama3-8b-sft-playpen-t0.0",
    "clem_version": "3.2.1"
  },
  "player_models": {
    "0": {
      "model_name": "llama3-8b-sft-playpen",
      "backend": "huggingface_local",
      "dtype": "bfloat16",
      "huggingface_id": "/home/users/iarefeva/playpen/runs/models/sft+lora/Meta-Llama-3.1-8B-Instruct/merged",
      "id_or_path": "/home/users/iarefeva/playpen/runs/models/sft+lora/Meta-Llama-3.1-8B-Instruct/merged",
      "lookup_source": "/home/users/iarefeva/playpen/model_registry.json",
      "model_config": {
        "requires_api_key": false,
        "premade_chat_template": true,
        "eos_to_cull": "<|eot_id|>"
      },
      "name": "llama3-8b-sft-playpen"
    }
  },
  "players": {
    "GM": {
      "game_role": "Game Master",
      "model_name": "programmatic"
    },
    "Player 1": {
      "game_role": "Answerer",
      "model_name": "llama3-8b-sft-playpen"
    }
  },
  "turns": [
    [
      {
        "from": "GM",
        "to": "Player 1",
        "timestamp": "2025-08-15T09:27:59.843656",
        "action": {
          "type": "send message",
          "content": "You are an expert in causal inference. The following question is not a typical commonsense query, but rather a meticulously designed question created by a professor specializing in causal inference, intended to assess the students' mastery of the course content.\nImagine a self-contained, hypothetical world with only the following conditions, and without any unmentioned factors or causal relationships: My decision has a direct effect on penguin mood and foot size. Penguin mood has a direct effect on foot size. We know that taking the elevator causes penguin saddness. taking the elevator or penguin happiness causes large feet. Would the person has large feet if taking the elevator instead of taking the stairs?\nStart your answer with 'Yes' or 'No', followed by additional reasoning or evidence to support your explanation.",
          "label": "context"
        }
      },
      {
        "from": "Player 1",
        "to": "GM",
        "timestamp": "2025-08-15T09:28:01.938405",
        "action": {
          "type": "get message",
          "content": "No\nThe person would not have large feet if taking the elevator instead of taking the stairs. The direct cause of large feet is penguin happiness, and the direct cause of penguin happiness is the person's decision. Since the person's decision is not taking the elevator, the penguin mood remains neutral, and the foot size remains small.||",
          "label": "response"
        }
      },
      {
        "from": "GM",
        "to": "GM",
        "timestamp": "2025-08-15T09:28:01.938472",
        "action": {
          "type": "parsed",
          "content": "No"
        }
      },
      {
        "from": "GM",
        "to": "GM",
        "timestamp": "2025-08-15T09:28:01.938487",
        "action": {
          "type": "target",
          "content": "yes"
        }
      },
      {
        "from": "GM",
        "to": "GM",
        "timestamp": "2025-08-15T09:28:01.938498",
        "action": {
          "type": "wrong label",
          "content": "game_result = LOSE"
        }
      }
    ]
  ],
  "Aborted": 0,
  "Lose": 1,
  "Success": 0,
  "Request Count": 1,
  "Parsed Request Count": 1,
  "Violated Request Count": 0
}