[
  {
    "timestamp": "2025-08-15T08:38:33.152360",
    "manipulated_prompt_obj": {
      "inputs": "<|begin_of_text|><|start_header_id|>system<|end_header_id|>\n\nCutting Knowledge Date: December 2023\nToday Date: 26 Jul 2024\n\n<|eot_id|><|start_header_id|>user<|end_header_id|>\n\nYou are an expert in causal inference. The following question is not a typical commonsense query, but rather a meticulously designed question created by a professor specializing in causal inference, intended to assess the students' mastery of the course content.\nImagine a self-contained, hypothetical world with only the following conditions, and without any unmentioned factors or causal relationships: Liking spicy food has a direct effect on occupation and salary. Skill has a direct effect on occupation and salary. Occupation has a direct effect on salary. Skill is unobserved. For individuals who do not like spicy food and blue-collar workers, the probability of high salary is 44%. For individuals who do not like spicy food and white-collar workers, the probability of high salary is 19%. For individuals who like spicy food and blue-collar workers, the probability of high salary is 44%. For individuals who like spicy food and white-collar workers, the probability of high salary is 19%. For individuals who do not like spicy food and with low skill levels, the probability of white-collar job is 71%. For individuals who do not like spicy food and with high skill levels, the probability of white-collar job is 32%. For individuals who like spicy food and with low skill levels, the probability of white-collar job is 65%. For individuals who like spicy food and with high skill levels, the probability of white-collar job is 37%. The overall probability of high skill level is 86%. If we disregard the mediation effect through occupation, would liking spicy food negatively affect salary?\nStart your answer with 'Yes' or 'No', followed by additional reasoning or evidence to support your explanation.<|eot_id|><|start_header_id|>assistant<|end_header_id|>\n\n",
      "max_new_tokens": 300,
      "temperature": 0.0,
      "return_full_text": false
    },
    "raw_response_obj": {
      "response": "<|begin_of_text|><|start_header_id|>system<|end_header_id|>\n\nCutting Knowledge Date: December 2023\nToday Date: 26 Jul 2024\n\n<|eot_id|><|start_header_id|>user<|end_header_id|>\n\nYou are an expert in causal inference. The following question is not a typical commonsense query, but rather a meticulously designed question created by a professor specializing in causal inference, intended to assess the students' mastery of the course content.\nImagine a self-contained, hypothetical world with only the following conditions, and without any unmentioned factors or causal relationships: Liking spicy food has a direct effect on occupation and salary. Skill has a direct effect on occupation and salary. Occupation has a direct effect on salary. Skill is unobserved. For individuals who do not like spicy food and blue-collar workers, the probability of high salary is 44%. For individuals who do not like spicy food and white-collar workers, the probability of high salary is 19%. For individuals who like spicy food and blue-collar workers, the probability of high salary is 44%. For individuals who like spicy food and white-collar workers, the probability of high salary is 19%. For individuals who do not like spicy food and with low skill levels, the probability of white-collar job is 71%. For individuals who do not like spicy food and with high skill levels, the probability of white-collar job is 32%. For individuals who like spicy food and with low skill levels, the probability of white-collar job is 65%. For individuals who like spicy food and with high skill levels, the probability of white-collar job is 37%. The overall probability of high skill level is 86%. If we disregard the mediation effect through occupation, would liking spicy food negatively affect salary?\nStart your answer with 'Yes' or 'No', followed by additional reasoning or evidence to support your explanation.<|eot_id|><|start_header_id|>assistant<|end_header_id|>\n\nNo\nThe direct relationship between liking spicy food and occupation is not the primary focus here. The key relationship is between occupation and salary, which is direct and positive. Liking spicy food does not directly affect occupation or salary; its primary role is as a mediator between skill and occupation. The direct relationship between skill and occupation is also positive. The negative relationship between liking spicy food and white-collar occupation is offset by the positive relationship between skill and white-collar occupation. The overall probability of white-collar occupation is higher for those who like spicy food (65% for those with low skill and 37% for those with high skill) than for those who do not like spicy food (71% for those with low skill and 32% for those with high skill). This suggests that, in this specific context, liking spicy food does not have a negative effect on white-collar occupation.<|eot_id|>",
      "clem_player": {
        "call_start": "2025-08-15 08:38:27.939142",
        "call_duration": "0:00:05.213168",
        "response": "No\nThe direct relationship between liking spicy food and occupation is not the primary focus here. The key relationship is between occupation and salary, which is direct and positive. Liking spicy food does not directly affect occupation or salary; its primary role is as a mediator between skill and occupation. The direct relationship between skill and occupation is also positive. The negative relationship between liking spicy food and white-collar occupation is offset by the positive relationship between skill and white-collar occupation. The overall probability of white-collar occupation is higher for those who like spicy food (65% for those with low skill and 37% for those with high skill) than for those who do not like spicy food (71% for those with low skill and 32% for those with high skill). This suggests that, in this specific context, liking spicy food does not have a negative effect on white-collar occupation.||",
        "model_name": "llama3-8b-sft-playpen"
      }
    }
  }
]